pdwind/__init__.py
pdwind-0.1.1.dist-info/DESCRIPTION.rst
pdwind-0.1.1.dist-info/METADATA
pdwind-0.1.1.dist-info/RECORD
pdwind-0.1.1.dist-info/WHEEL
pdwind-0.1.1.dist-info/metadata.json
pdwind-0.1.1.dist-info/top_level.txt
