Metadata-Version: 2.0
Name: pdwind
Version: 0.1.1
Summary: Pandas adapter for WindPy
Home-page: https://github.com/fuchen/pdwind
Author: fuchen
Author-email: ink.pad@163.com
License: UNKNOWN
Platform: UNKNOWN
